silvanus/__init__.py
silvanus/integration/__init__.py
silvanus/integration/duck/__init__.py
silvanus/integration/duck/filters.py
silvanus/integration/http/__init__.py
silvanus/integration/http/base.py
silvanus/routing/__init__.py
silvanus/routing/simple.py
silvanus/strategy/__init__.py
silvanus/strategy/base.py
silvanus/strategy/routers/__init__.py
silvanus/strategy/routers/all.py
silvanus/strategy/routers/base.py
silvanus/strategy/routers/first.py
silvanus/structures/__init__.py
silvanus/structures/base.py
silvanus-0.1.0b0.dist-info/METADATA
silvanus-0.1.0b0.dist-info/WHEEL
silvanus-0.1.0b0.dist-info/RECORD
