Metadata-Version: 2.4
Name: silvanus
Version: 0.1.0b0
Summary: A simple library for routing with a tree-like structure
License: MIT
Author: Alexandr Bortnik
Author-email: sambonsttt@gmail.com
Requires-Python: >=3.9,<4.0
Classifier: Intended Audience :: Developers
Classifier: License :: OSI Approved :: MIT License
Classifier: Operating System :: OS Independent
Classifier: Programming Language :: Python :: 3
Classifier: Programming Language :: Python :: 3.9
Classifier: Programming Language :: Python :: 3.10
Classifier: Programming Language :: Python :: 3.11
Classifier: Programming Language :: Python :: 3.12
Classifier: Programming Language :: Python :: 3.13
Classifier: Programming Language :: Python :: 3.14
Project-URL: Bug Tracker, https://github.com/Sethis/silvanus/issues
Project-URL: Homepage, https://github.com/Sethis/silvanus
